sheetsorm/__init__.py
sheetsorm/decorators.py
sheetsorm/models.py
sheetsorm/orm.py
sheetsorm/repository.py
sheetsorm/util.py
sheetsorm-0.18.3.dist-info/LICENSE
sheetsorm-0.18.3.dist-info/METADATA
sheetsorm-0.18.3.dist-info/WHEEL
sheetsorm-0.18.3.dist-info/top_level.txt
sheetsorm-0.18.3.dist-info/RECORD
