Metadata-Version: 2.1
Name: sheetsorm
Version: 0.18.3
Summary: SheetsORM is a simple micro ORM extension for gspread.
Home-page: https://github.com/pedrohenriquebr/sheetsorm
Author: Pedro Braga
Author-email: pedrohenriquebraga735@gmail.com
License: UNKNOWN
Project-URL: Bug Tracker, https://github.com/pedrohenriquebr/sheetsorm/issues
Platform: UNKNOWN
Classifier: Programming Language :: Python
Classifier: Programming Language :: Python :: 3
Classifier: License :: OSI Approved :: MIT License
Classifier: Operating System :: OS Independent
Classifier: Intended Audience :: Developers
Classifier: Topic :: Software Development :: Libraries :: Python Modules
Requires-Python: >=3.6
License-File: LICENSE
Requires-Dist: gspread (==4.0.1)
Requires-Dist: oauth2client (==4.1.3)
Requires-Dist: pandas (==1.3.1)
